<resources>

    <!-- Base application theme. -->
    <style name="AppTheme" parent="Theme.MaterialComponents.Light">
        <!-- Customize your theme here. -->
        <item name="colorPrimary">@color/colorPrimary</item>
        <item name="colorPrimaryDark">@color/colorPrimaryDark</item>m>
        <item name="colorAccent">@color/tm_orange</item>
        <item name="windowNoTitle">true</item>
        <item name="windowActionBar">false</item>
        <item name="windowActionModeOverlay">false</item>
        <item name="android:windowBackground">@color/white</item>
        <item name="android:statusBarColor">@android:color/transparent</item>
        <item name="android:textCursorDrawable">@null</item>
        <item name="android:forceDarkAllowed">false</item>
        <item name="android:windowIsTranslucent">false</item>
        <item name="android:windowContentOverlay">@null</item>
        <item name="android:windowNoTitle">true</item>
        <item name="android:windowLightStatusBar">true</item>
    </style>

    <style name="AppTheme.NoActionBar">
        <item name="windowActionBar">false</item>
        <item name="windowNoTitle">true</item>
    </style>

    <style name="AppTheme.AppBarOverlay" parent="ThemeOverlay.MaterialComponents.ActionBar">
      <item name="android:fontFamily">@font/oswald</item>
    </style>

    <style name="AppTheme.PopupOverlay" parent="ThemeOverlay.MaterialComponents.Light" />

</resources>

